pavilion_cms/__init__.py
pavilion_cms/__version__.py
pavilion_cms/author.py
pavilion_cms/category.py
pavilion_cms/client.py
pavilion_cms/exceptions.py
pavilion_cms/posts.py
pavilion_cms/tag.py
pavilion_cms/utils.py
pavilioncms_python-1.0.1.dist-info/METADATA
pavilioncms_python-1.0.1.dist-info/WHEEL
pavilioncms_python-1.0.1.dist-info/top_level.txt
pavilioncms_python-1.0.1.dist-info/RECORD
